{
  "image": "quay.io/keycloak/keycloak@sha256:f8ade94c1d0ad2f2fa7734a455fee5392764f402c43ca35e9af6bf63a2541dc9",
  "args": [
    "start"
  ],
  "env": [
    {
      "name": "KEYCLOAK_ADMIN",
      "has_value": true,
      "has_valueFrom": false,
      "value": "admin",
      "secret": null,
      "key": null
    },
    {
      "name": "KEYCLOAK_ADMIN_PASSWORD",
      "has_value": false,
      "has_valueFrom": true,
      "value": null,
      "secret": "traffic-credentials",
      "key": "KEYCLOAK_ADMIN_PASSWORD"
    },
    {
      "name": "KC_HOSTNAME_STRICT",
      "has_value": true,
      "has_valueFrom": false,
      "value": "false",
      "secret": null,
      "key": null
    },
    {
      "name": "KC_PROXY_HEADERS",
      "has_value": true,
      "has_valueFrom": false,
      "value": "xforwarded",
      "secret": null,
      "key": null
    },
    {
      "name": "KC_HEALTH_ENABLED",
      "has_value": true,
      "has_valueFrom": false,
      "value": "true",
      "secret": null,
      "key": null
    },
    {
      "name": "KC_HTTPS_CERTIFICATE_FILE",
      "has_value": true,
      "has_valueFrom": false,
      "value": "/etc/keycloak/tls/tls.crt",
      "secret": null,
      "key": null
    },
    {
      "name": "KC_HTTPS_CERTIFICATE_KEY_FILE",
      "has_value": true,
      "has_valueFrom": false,
      "value": "/etc/keycloak/tls/tls.key",
      "secret": null,
      "key": null
    }
  ]
}
